{
  "total": 100,
  "posts_per_day": 9,
  "posts": [
    {
      "index": 0,
      "metric": "Daily Screen Time",
      "hook": "No way, there's official ranks for screen time now..",
      "caption": "No way, there's official ranks for screen time now..\n\nsend this to your phone-addicted friend \ud83d\udc80\n\nDownload Seneca Chat - link in bio",
      "video_file": "social-scheduler/videos/00-daily-screen-time.mp4",
      "ig_published": true,
      "fb_published": false,
      "ig_media_id": "17992482902947212"
    },
    {
      "index": 1,
      "metric": "Daily Screen Time",
      "hook": "Be honest.. what rank is your screen time?",
      "caption": "Be honest.. what rank is your screen time?\n\nmost people won't post theirs \ud83d\ude2c\n\nDownload Seneca Chat - link in bio",
      "video_file": "social-scheduler/videos/01-daily-screen-time.mp4",
      "ig_published": true,
      "fb_published": false,
      "ig_media_id": "18110539096757763"
    },
    {
      "index": 2,
      "metric": "Daily Screen Time",
      "hook": "POV: you checked your screen time report today..",
      "caption": "POV: you checked your screen time report today..\n\nand you're not proud of it \ud83d\ude2d\n\nDownload Seneca Chat - link in bio",
      "video_file": "social-scheduler/videos/02-daily-screen-time.mp4",
      "ig_published": true,
      "fb_published": false,
      "ig_media_id": "17930436474057154"
    },
    {
      "index": 3,
      "metric": "Daily Screen Time",
      "hook": "Your screen time says a lot about your discipline..",
      "caption": "Your screen time says a lot about your discipline..\n\nwhere do you rank? \ud83d\udc40\n\nDownload Seneca Chat - link in bio",
      "video_file": "social-scheduler/videos/03-daily-screen-time.mp4",
      "ig_published": true,
      "fb_published": false,
      "ig_media_id": "18095071496054876"
    },
    {
      "index": 4,
      "metric": "Daily Screen Time",
      "hook": "If screen time had ranks, most people would be Bronze..",
      "caption": "If screen time had ranks, most people would be Bronze..\n\nprove me wrong \ud83e\udd37\n\nDownload Seneca Chat - link in bio",
      "video_file": "social-scheduler/videos/04-daily-screen-time.mp4",
      "ig_published": true,
      "fb_published": false,
      "ig_media_id": "18261525844293513"
    },
    {
      "index": 5,
      "metric": "Daily Screen Time",
      "hook": "Tag someone who needs to see their screen time rank..",
      "caption": "Tag someone who needs to see their screen time rank..\n\nthey already know who they are \ud83d\udcf1\n\nDownload Seneca Chat - link in bio",
      "video_file": "social-scheduler/videos/05-daily-screen-time.mp4",
      "ig_published": true,
      "fb_published": false,
      "ig_media_id": "18079115735374352"
    },
    {
      "index": 6,
      "metric": "Daily Screen Time",
      "hook": "Screen time rankings just dropped..",
      "caption": "Screen time rankings just dropped..\n\nand most of you aren't making it past Gold \ud83d\udc80\n\nDownload Seneca Chat - link in bio",
      "video_file": "social-scheduler/videos/06-daily-screen-time.mp4",
      "ig_published": true,
      "fb_published": false,
      "ig_media_id": "18084111194593734"
    },
    {
      "index": 7,
      "metric": "Daily Screen Time",
      "hook": "Your screen time is the scoreboard nobody asked for..",
      "caption": "Your screen time is the scoreboard nobody asked for..\n\nbut everyone needs to see \ud83d\udcca\n\nDownload Seneca Chat - link in bio",
      "video_file": "social-scheduler/videos/07-daily-screen-time.mp4",
      "ig_published": true,
      "fb_published": false,
      "ig_media_id": "18367228894161522"
    },
    {
      "index": 8,
      "metric": "Daily Screen Time",
      "hook": "I know someone who's definitely Bronze on this..",
      "caption": "I know someone who's definitely Bronze on this..\n\ntag them, they need this wake-up call \ud83d\ude34\n\nDownload Seneca Chat - link in bio",
      "video_file": "social-scheduler/videos/08-daily-screen-time.mp4",
      "ig_published": true,
      "fb_published": false,
      "ig_media_id": "18573165787050712"
    },
    {
      "index": 9,
      "metric": "Daily Screen Time",
      "hook": "Imagine flexing your screen time like a rank..",
      "caption": "Imagine flexing your screen time like a rank..\n\nonly Iridescent players move in silence \ud83e\udd2b\n\nDownload Seneca Chat - link in bio",
      "video_file": "social-scheduler/videos/09-daily-screen-time.mp4",
      "ig_published": true,
      "fb_published": false,
      "ig_media_id": "18061135397342865"
    },
    {
      "index": 10,
      "metric": "Meditation Mins This Month",
      "hook": "No way, there's official ranks for meditation now..",
      "caption": "No way, there's official ranks for meditation now..\n\nsend this to someone who needs inner peace \ud83d\udc80\n\nDownload Seneca Chat - link in bio",
      "video_file": "social-scheduler/videos/10-meditation-mins-this-month.mp4",
      "ig_published": true,
      "fb_published": false,
      "ig_media_id": "17982774401962247"
    },
    {
      "index": 11,
      "metric": "Meditation Mins This Month",
      "hook": "Be honest.. how many minutes did you meditate this month?",
      "caption": "Be honest.. how many minutes did you meditate this month?\n\nmost people can't even sit still for 5 \ud83d\ude2c\n\nDownload Seneca Chat - link in bio",
      "video_file": "social-scheduler/videos/11-meditation-mins-this-month.mp4",
      "ig_published": true,
      "fb_published": false,
      "ig_media_id": "17876849085520351"
    },
    {
      "index": 12,
      "metric": "Meditation Mins This Month",
      "hook": "Your meditation minutes reveal your mental strength..",
      "caption": "Your meditation minutes reveal your mental strength..\n\nwhere do you land? \ud83e\uddd8\n\nDownload Seneca Chat - link in bio",
      "video_file": "social-scheduler/videos/12-meditation-mins-this-month.mp4",
      "ig_published": true,
      "fb_published": false,
      "ig_media_id": "18082099031458825"
    },
    {
      "index": 13,
      "metric": "Meditation Mins This Month",
      "hook": "If meditation had a leaderboard..",
      "caption": "If meditation had a leaderboard..\n\nmost people wouldn't even qualify \ud83d\udc80\n\nDownload Seneca Chat - link in bio",
      "video_file": "social-scheduler/videos/13-meditation-mins-this-month.mp4",
      "ig_published": true,
      "fb_published": false,
      "ig_media_id": "18121858054593234"
    },
    {
      "index": 14,
      "metric": "Meditation Mins This Month",
      "hook": "People who meditate daily are built different..",
      "caption": "People who meditate daily are built different..\n\nwhat rank are you? \ud83e\udde0\n\nDownload Seneca Chat - link in bio",
      "video_file": "social-scheduler/videos/14-meditation-mins-this-month.mp4",
      "ig_published": true,
      "fb_published": false,
      "ig_media_id": "18083927792252413"
    },
    {
      "index": 15,
      "metric": "Meditation Mins This Month",
      "hook": "POV: you actually tracked your meditation this month..",
      "caption": "POV: you actually tracked your meditation this month..\n\nand now you know the truth \ud83d\ude33\n\nDownload Seneca Chat - link in bio",
      "video_file": "social-scheduler/videos/15-meditation-mins-this-month.mp4",
      "ig_published": true,
      "fb_published": false,
      "ig_media_id": "18057165809679768"
    },
    {
      "index": 16,
      "metric": "Meditation Mins This Month",
      "hook": "Meditation rankings just dropped..",
      "caption": "Meditation rankings just dropped..\n\nsend this to someone who says they meditate but doesn't \ud83d\udc40\n\nDownload Seneca Chat - link in bio",
      "video_file": "social-scheduler/videos/16-meditation-mins-this-month.mp4",
      "ig_published": true,
      "fb_published": false,
      "ig_media_id": "18077907446527740"
    },
    {
      "index": 17,
      "metric": "Meditation Mins This Month",
      "hook": "The people who need meditation the most don't do it..",
      "caption": "The people who need meditation the most don't do it..\n\ntag them \ud83e\udee0\n\nDownload Seneca Chat - link in bio",
      "video_file": "social-scheduler/videos/17-meditation-mins-this-month.mp4",
      "ig_published": true,
      "fb_published": false,
      "ig_media_id": "18034171220788328"
    },
    {
      "index": 18,
      "metric": "Meditation Mins This Month",
      "hook": "Still think meditation is a waste of time?",
      "caption": "Still think meditation is a waste of time?\n\ncheck your rank and get back to me \ud83d\ude4f\n\nDownload Seneca Chat - link in bio",
      "video_file": "social-scheduler/videos/18-meditation-mins-this-month.mp4",
      "ig_published": true,
      "fb_published": false,
      "ig_media_id": "18061170995362591"
    },
    {
      "index": 19,
      "metric": "Meditation Mins This Month",
      "hook": "Your meditation rank says everything about your peace..",
      "caption": "Your meditation rank says everything about your peace..\n\nno cap \ud83e\uddd8\u200d\u2642\ufe0f\n\nDownload Seneca Chat - link in bio",
      "video_file": "social-scheduler/videos/19-meditation-mins-this-month.mp4",
      "ig_published": true,
      "fb_published": false,
      "ig_media_id": "17883194388466836"
    },
    {
      "index": 20,
      "metric": "Reflections This Month",
      "hook": "No way, there's official ranks for journaling now..",
      "caption": "No way, there's official ranks for journaling now..\n\nsend this to your overthinking friend \ud83d\udc80\n\nDownload Seneca Chat - link in bio",
      "video_file": "social-scheduler/videos/20-reflections-this-month.mp4",
      "ig_published": true,
      "fb_published": false,
      "ig_media_id": "18365265091160427"
    },
    {
      "index": 21,
      "metric": "Reflections This Month",
      "hook": "How many times did you journal this month? Be honest..",
      "caption": "How many times did you journal this month? Be honest..\n\nthought so \ud83d\udcd3\n\nDownload Seneca Chat - link in bio",
      "video_file": "social-scheduler/videos/21-reflections-this-month.mp4",
      "ig_published": true,
      "fb_published": false,
      "ig_media_id": "18110108278766158"
    },
    {
      "index": 22,
      "metric": "Reflections This Month",
      "hook": "Journaling ranks just dropped..",
      "caption": "Journaling ranks just dropped..\n\nmost people can't even write one honest sentence \ud83d\udc80\n\nDownload Seneca Chat - link in bio",
      "video_file": "social-scheduler/videos/22-reflections-this-month.mp4",
      "ig_published": true,
      "fb_published": false,
      "ig_media_id": "18175712809386730"
    },
    {
      "index": 23,
      "metric": "Reflections This Month",
      "hook": "The people with the calmest minds journal daily..",
      "caption": "The people with the calmest minds journal daily..\n\nwhere do you rank? \u270d\ufe0f\n\nDownload Seneca Chat - link in bio",
      "video_file": "social-scheduler/videos/23-reflections-this-month.mp4",
      "ig_published": true,
      "fb_published": false,
      "ig_media_id": "18105662617722125"
    },
    {
      "index": 24,
      "metric": "Reflections This Month",
      "hook": "If journaling had a scoreboard..",
      "caption": "If journaling had a scoreboard..\n\nmost of you would be unranked \ud83d\ude2c\n\nDownload Seneca Chat - link in bio",
      "video_file": "social-scheduler/videos/24-reflections-this-month.mp4",
      "ig_published": true,
      "fb_published": false,
      "ig_media_id": "18100066331477010"
    },
    {
      "index": 25,
      "metric": "Reflections This Month",
      "hook": "POV: you say you journal but only wrote once this month..",
      "caption": "POV: you say you journal but only wrote once this month..\n\nBronze behaviour \ud83e\udd49\n\nDownload Seneca Chat - link in bio",
      "video_file": "social-scheduler/videos/25-reflections-this-month.mp4",
      "ig_published": true,
      "fb_published": false,
      "ig_media_id": "17963336339901391"
    },
    {
      "index": 26,
      "metric": "Reflections This Month",
      "hook": "Tag someone who says they journal but never does..",
      "caption": "Tag someone who says they journal but never does..\n\nthey need to see their rank \ud83d\udcdd\n\nDownload Seneca Chat - link in bio",
      "video_file": "social-scheduler/videos/26-reflections-this-month.mp4",
      "ig_published": true,
      "fb_published": false,
      "ig_media_id": "17971786229861611"
    },
    {
      "index": 27,
      "metric": "Reflections This Month",
      "hook": "Writing your thoughts down is a cheat code..",
      "caption": "Writing your thoughts down is a cheat code..\n\nbut most people still don't do it \ud83e\udd26\n\nDownload Seneca Chat - link in bio",
      "video_file": "social-scheduler/videos/27-reflections-this-month.mp4",
      "ig_published": true,
      "fb_published": false,
      "ig_media_id": "18111945709666074"
    },
    {
      "index": 28,
      "metric": "Reflections This Month",
      "hook": "Your reflection count reveals your self-awareness..",
      "caption": "Your reflection count reveals your self-awareness..\n\nwhat's your rank? \ud83e\ude9e\n\nDownload Seneca Chat - link in bio",
      "video_file": "social-scheduler/videos/28-reflections-this-month.mp4",
      "ig_published": true,
      "fb_published": false,
      "ig_media_id": "18093163636857734"
    },
    {
      "index": 29,
      "metric": "Reflections This Month",
      "hook": "Iridescent journalers are a different breed..",
      "caption": "Iridescent journalers are a different breed..\n\n30 reflections in a month is elite \ud83d\udc51\n\nDownload Seneca Chat - link in bio",
      "video_file": "social-scheduler/videos/29-reflections-this-month.mp4",
      "ig_published": true,
      "fb_published": false,
      "ig_media_id": "18115035100728272"
    },
    {
      "index": 30,
      "metric": "Books Read This Year",
      "hook": "No way, there's official ranks for philosophy now..",
      "caption": "No way, there's official ranks for philosophy now..\n\nsend this to your book nerd friend \ud83d\udc80\n\nDownload Seneca Chat - link in bio",
      "video_file": "social-scheduler/videos/30-books-read-this-year.mp4",
      "ig_published": true,
      "fb_published": false,
      "ig_media_id": "18057210824452431"
    },
    {
      "index": 31,
      "metric": "Books Read This Year",
      "hook": "How many books have you actually read this year?",
      "caption": "How many books have you actually read this year?\n\naudiobooks don't count \ud83d\udcda\n\nDownload Seneca Chat - link in bio",
      "video_file": "social-scheduler/videos/31-books-read-this-year.mp4",
      "ig_published": true,
      "fb_published": false,
      "ig_media_id": "17994929711924006"
    },
    {
      "index": 32,
      "metric": "Books Read This Year",
      "hook": "Reading ranks just dropped..",
      "caption": "Reading ranks just dropped..\n\nand buying books doesn't count as reading them \ud83d\udc80\n\nDownload Seneca Chat - link in bio",
      "video_file": "social-scheduler/videos/32-books-read-this-year.mp4",
      "ig_published": true,
      "fb_published": false,
      "ig_media_id": "18111711589707022"
    },
    {
      "index": 33,
      "metric": "Books Read This Year",
      "hook": "The smartest people you know read 2 books a month..",
      "caption": "The smartest people you know read 2 books a month..\n\nwhere do you rank? \ud83d\udcd6\n\nDownload Seneca Chat - link in bio",
      "video_file": "social-scheduler/videos/33-books-read-this-year.mp4",
      "ig_published": true,
      "fb_published": false,
      "ig_media_id": "18094295831092776"
    },
    {
      "index": 34,
      "metric": "Books Read This Year",
      "hook": "Your bookshelf is judging you right now..",
      "caption": "Your bookshelf is judging you right now..\n\nhow many did you actually finish? \ud83d\udc40\n\nDownload Seneca Chat - link in bio",
      "video_file": "social-scheduler/videos/34-books-read-this-year.mp4",
      "ig_published": true,
      "fb_published": false,
      "ig_media_id": "18073091816536902"
    },
    {
      "index": 35,
      "metric": "Books Read This Year",
      "hook": "POV: someone asks how many books you've read this year..",
      "caption": "POV: someone asks how many books you've read this year..\n\nand you have to lie \ud83d\ude05\n\nDownload Seneca Chat - link in bio",
      "video_file": "social-scheduler/videos/35-books-read-this-year.mp4",
      "ig_published": true,
      "fb_published": false,
      "ig_media_id": "18300360724263958"
    },
    {
      "index": 36,
      "metric": "Books Read This Year",
      "hook": "Tag someone who buys books but never reads them..",
      "caption": "Tag someone who buys books but never reads them..\n\ntheir shelf is just decoration at this point \ud83e\udee0\n\nDownload Seneca Chat - link in bio",
      "video_file": "social-scheduler/videos/36-books-read-this-year.mp4",
      "ig_published": true,
      "fb_published": false,
      "ig_media_id": "18102682919490694"
    },
    {
      "index": 37,
      "metric": "Books Read This Year",
      "hook": "Readers are leaders.. but most people aren't reading..",
      "caption": "Readers are leaders.. but most people aren't reading..\n\nwhat's your rank? \ud83c\udfc6\n\nDownload Seneca Chat - link in bio",
      "video_file": "social-scheduler/videos/37-books-read-this-year.mp4",
      "ig_published": true,
      "fb_published": false,
      "ig_media_id": "17877811569533667"
    },
    {
      "index": 38,
      "metric": "Books Read This Year",
      "hook": "24 books a year is only 2 a month..",
      "caption": "24 books a year is only 2 a month..\n\nand most people still can't do it \ud83e\udd37\n\nDownload Seneca Chat - link in bio",
      "video_file": "social-scheduler/videos/38-books-read-this-year.mp4",
      "ig_published": true,
      "fb_published": false,
      "ig_media_id": "18078800741102359"
    },
    {
      "index": 39,
      "metric": "Books Read This Year",
      "hook": "If reading had competitive ranks..",
      "caption": "If reading had competitive ranks..\n\nwhat tier would you be in? \ud83d\udcd5\n\nDownload Seneca Chat - link in bio",
      "video_file": "social-scheduler/videos/39-books-read-this-year.mp4",
      "ig_published": true,
      "fb_published": false,
      "ig_media_id": "18097739450058317"
    },
    {
      "index": 40,
      "metric": "Daily Ritual Streak",
      "hook": "No way, there's official ranks for daily streaks now..",
      "caption": "No way, there's official ranks for daily streaks now..\n\nsend this to someone who can't stay consistent \ud83d\udc80\n\nDownload Seneca Chat - link in bio",
      "video_file": "social-scheduler/videos/40-daily-ritual-streak.mp4",
      "ig_published": true,
      "fb_published": false,
      "ig_media_id": "17851337655640416"
    },
    {
      "index": 41,
      "metric": "Daily Ritual Streak",
      "hook": "Be honest.. how long is your longest streak?",
      "caption": "Be honest.. how long is your longest streak?\n\nquitting on day 4 doesn't count \ud83d\ude2c\n\nDownload Seneca Chat - link in bio",
      "video_file": "social-scheduler/videos/41-daily-ritual-streak.mp4",
      "ig_published": false,
      "fb_published": false
    },
    {
      "index": 42,
      "metric": "Daily Ritual Streak",
      "hook": "Consistency rankings just dropped..",
      "caption": "Consistency rankings just dropped..\n\nmost of you won't make it past Gold \ud83d\udc80\n\nDownload Seneca Chat - link in bio",
      "video_file": "social-scheduler/videos/42-daily-ritual-streak.mp4",
      "ig_published": false,
      "fb_published": false
    },
    {
      "index": 43,
      "metric": "Daily Ritual Streak",
      "hook": "A 365-day streak is not luck, it's identity..",
      "caption": "A 365-day streak is not luck, it's identity..\n\nwhat's your rank? \ud83d\udd25\n\nDownload Seneca Chat - link in bio",
      "video_file": "social-scheduler/videos/43-daily-ritual-streak.mp4",
      "ig_published": false,
      "fb_published": false
    },
    {
      "index": 44,
      "metric": "Daily Ritual Streak",
      "hook": "Your streak length reveals your discipline..",
      "caption": "Your streak length reveals your discipline..\n\nno excuses, where do you land? \ud83d\udcaa\n\nDownload Seneca Chat - link in bio",
      "video_file": "social-scheduler/videos/44-daily-ritual-streak.mp4",
      "ig_published": false,
      "fb_published": false
    },
    {
      "index": 45,
      "metric": "Daily Ritual Streak",
      "hook": "Tag someone who starts streaks but never keeps them..",
      "caption": "Tag someone who starts streaks but never keeps them..\n\nthey restart every Monday \ud83d\ude02\n\nDownload Seneca Chat - link in bio",
      "video_file": "social-scheduler/videos/45-daily-ritual-streak.mp4",
      "ig_published": false,
      "fb_published": false
    },
    {
      "index": 46,
      "metric": "Daily Ritual Streak",
      "hook": "POV: you broke your streak after 3 days.. again..",
      "caption": "POV: you broke your streak after 3 days.. again..\n\nBronze behaviour \ud83e\udd49\n\nDownload Seneca Chat - link in bio",
      "video_file": "social-scheduler/videos/46-daily-ritual-streak.mp4",
      "ig_published": false,
      "fb_published": false
    },
    {
      "index": 47,
      "metric": "Daily Ritual Streak",
      "hook": "If daily habits had a ranked ladder..",
      "caption": "If daily habits had a ranked ladder..\n\nmost people would be hard stuck Bronze \ud83d\udcc9\n\nDownload Seneca Chat - link in bio",
      "video_file": "social-scheduler/videos/47-daily-ritual-streak.mp4",
      "ig_published": false,
      "fb_published": false
    },
    {
      "index": 48,
      "metric": "Daily Ritual Streak",
      "hook": "The gap between Bronze and Iridescent is discipline..",
      "caption": "The gap between Bronze and Iridescent is discipline..\n\nnothing else \ud83e\udde0\n\nDownload Seneca Chat - link in bio",
      "video_file": "social-scheduler/videos/48-daily-ritual-streak.mp4",
      "ig_published": false,
      "fb_published": false
    },
    {
      "index": 49,
      "metric": "Daily Ritual Streak",
      "hook": "365 days without breaking the chain..",
      "caption": "365 days without breaking the chain..\n\nonly Iridescent players understand \ud83d\udc51\n\nDownload Seneca Chat - link in bio",
      "video_file": "social-scheduler/videos/49-daily-ritual-streak.mp4",
      "ig_published": false,
      "fb_published": false
    },
    {
      "index": 50,
      "metric": "Breathwork Mins This Week",
      "hook": "No way, there's official ranks for breathwork now..",
      "caption": "No way, there's official ranks for breathwork now..\n\nsend this to your stressed friend \ud83d\udc80\n\nDownload Seneca Chat - link in bio",
      "video_file": "social-scheduler/videos/50-breathwork-mins-this-week.mp4",
      "ig_published": false,
      "fb_published": false
    },
    {
      "index": 51,
      "metric": "Breathwork Mins This Week",
      "hook": "How many minutes of breathwork did you do this week?",
      "caption": "How many minutes of breathwork did you do this week?\n\nbe honest \ud83c\udf2c\ufe0f\n\nDownload Seneca Chat - link in bio",
      "video_file": "social-scheduler/videos/51-breathwork-mins-this-week.mp4",
      "ig_published": false,
      "fb_published": false
    },
    {
      "index": 52,
      "metric": "Breathwork Mins This Week",
      "hook": "Breathwork rankings just dropped..",
      "caption": "Breathwork rankings just dropped..\n\nyour nervous system is begging you to rank up \ud83d\udc80\n\nDownload Seneca Chat - link in bio",
      "video_file": "social-scheduler/videos/52-breathwork-mins-this-week.mp4",
      "ig_published": false,
      "fb_published": false
    },
    {
      "index": 53,
      "metric": "Breathwork Mins This Week",
      "hook": "People who do breathwork daily are unshakeable..",
      "caption": "People who do breathwork daily are unshakeable..\n\nwhat's your rank? \ud83e\uddca\n\nDownload Seneca Chat - link in bio",
      "video_file": "social-scheduler/videos/53-breathwork-mins-this-week.mp4",
      "ig_published": false,
      "fb_published": false
    },
    {
      "index": 54,
      "metric": "Breathwork Mins This Week",
      "hook": "Your stress levels are directly tied to this rank..",
      "caption": "Your stress levels are directly tied to this rank..\n\nand you know it \ud83d\ude24\n\nDownload Seneca Chat - link in bio",
      "video_file": "social-scheduler/videos/54-breathwork-mins-this-week.mp4",
      "ig_published": false,
      "fb_published": false
    },
    {
      "index": 55,
      "metric": "Breathwork Mins This Week",
      "hook": "Tag someone who's always stressed but never breathes..",
      "caption": "Tag someone who's always stressed but never breathes..\n\nthey need this \ud83e\udec1\n\nDownload Seneca Chat - link in bio",
      "video_file": "social-scheduler/videos/55-breathwork-mins-this-week.mp4",
      "ig_published": false,
      "fb_published": false
    },
    {
      "index": 56,
      "metric": "Breathwork Mins This Week",
      "hook": "POV: you learned box breathing and never looked back..",
      "caption": "POV: you learned box breathing and never looked back..\n\nChampion behaviour \ud83c\udfc6\n\nDownload Seneca Chat - link in bio",
      "video_file": "social-scheduler/videos/56-breathwork-mins-this-week.mp4",
      "ig_published": false,
      "fb_published": false
    },
    {
      "index": 57,
      "metric": "Breathwork Mins This Week",
      "hook": "The most underrated habit in self-improvement..",
      "caption": "The most underrated habit in self-improvement..\n\nand most people don't even try it \ud83e\udd26\n\nDownload Seneca Chat - link in bio",
      "video_file": "social-scheduler/videos/57-breathwork-mins-this-week.mp4",
      "ig_published": false,
      "fb_published": false
    },
    {
      "index": 58,
      "metric": "Breathwork Mins This Week",
      "hook": "90 minutes of breathwork a week changes your life..",
      "caption": "90 minutes of breathwork a week changes your life..\n\nbut most people can't even do 5 \ud83d\udc80\n\nDownload Seneca Chat - link in bio",
      "video_file": "social-scheduler/videos/58-breathwork-mins-this-week.mp4",
      "ig_published": false,
      "fb_published": false
    },
    {
      "index": 59,
      "metric": "Breathwork Mins This Week",
      "hook": "If calm had a ranking system..",
      "caption": "If calm had a ranking system..\n\nIridescent breathworkers would be at the top \ud83e\uddd8\n\nDownload Seneca Chat - link in bio",
      "video_file": "social-scheduler/videos/59-breathwork-mins-this-week.mp4",
      "ig_published": false,
      "fb_published": false
    },
    {
      "index": 60,
      "metric": "Pages Read Today",
      "hook": "No way, there's official ranks for reading now..",
      "caption": "No way, there's official ranks for reading now..\n\nsend this to someone who says they'll read more \ud83d\udc80\n\nDownload Seneca Chat - link in bio",
      "video_file": "social-scheduler/videos/60-pages-read-today.mp4",
      "ig_published": false,
      "fb_published": false
    },
    {
      "index": 61,
      "metric": "Pages Read Today",
      "hook": "How many pages did you read today? Be honest..",
      "caption": "How many pages did you read today? Be honest..\n\nscrolling Twitter doesn't count \ud83d\udcf1\n\nDownload Seneca Chat - link in bio",
      "video_file": "social-scheduler/videos/61-pages-read-today.mp4",
      "ig_published": false,
      "fb_published": false
    },
    {
      "index": 62,
      "metric": "Pages Read Today",
      "hook": "Daily reading ranks just dropped..",
      "caption": "Daily reading ranks just dropped..\n\nmost people didn't read a single page today \ud83d\udc80\n\nDownload Seneca Chat - link in bio",
      "video_file": "social-scheduler/videos/62-pages-read-today.mp4",
      "ig_published": false,
      "fb_published": false
    },
    {
      "index": 63,
      "metric": "Pages Read Today",
      "hook": "100 pages a day sounds crazy until you try it..",
      "caption": "100 pages a day sounds crazy until you try it..\n\nIridescent readers are different \ud83d\udcd6\n\nDownload Seneca Chat - link in bio",
      "video_file": "social-scheduler/videos/63-pages-read-today.mp4",
      "ig_published": false,
      "fb_published": false
    },
    {
      "index": 64,
      "metric": "Pages Read Today",
      "hook": "Your daily page count reveals your growth rate..",
      "caption": "Your daily page count reveals your growth rate..\n\nwhere do you rank? \ud83d\udcda\n\nDownload Seneca Chat - link in bio",
      "video_file": "social-scheduler/videos/64-pages-read-today.mp4",
      "ig_published": false,
      "fb_published": false
    },
    {
      "index": 65,
      "metric": "Pages Read Today",
      "hook": "Tag someone who hasn't read a book since school..",
      "caption": "Tag someone who hasn't read a book since school..\n\nthey're not even Bronze \ud83d\ude02\n\nDownload Seneca Chat - link in bio",
      "video_file": "social-scheduler/videos/65-pages-read-today.mp4",
      "ig_published": false,
      "fb_published": false
    },
    {
      "index": 66,
      "metric": "Pages Read Today",
      "hook": "POV: you replaced 30 mins of scrolling with reading..",
      "caption": "POV: you replaced 30 mins of scrolling with reading..\n\ninstant rank up \ud83d\udcc8\n\nDownload Seneca Chat - link in bio",
      "video_file": "social-scheduler/videos/66-pages-read-today.mp4",
      "ig_published": false,
      "fb_published": false
    },
    {
      "index": 67,
      "metric": "Pages Read Today",
      "hook": "If knowledge had a ranking system..",
      "caption": "If knowledge had a ranking system..\n\ndaily readers would dominate \ud83e\udde0\n\nDownload Seneca Chat - link in bio",
      "video_file": "social-scheduler/videos/67-pages-read-today.mp4",
      "ig_published": false,
      "fb_published": false
    },
    {
      "index": 68,
      "metric": "Pages Read Today",
      "hook": "The top 1% reads every single day..",
      "caption": "The top 1% reads every single day..\n\nwhat's your page count? \ud83d\udc40\n\nDownload Seneca Chat - link in bio",
      "video_file": "social-scheduler/videos/68-pages-read-today.mp4",
      "ig_published": false,
      "fb_published": false
    },
    {
      "index": 69,
      "metric": "Pages Read Today",
      "hook": "Reading pages daily is the easiest flex..",
      "caption": "Reading pages daily is the easiest flex..\n\nand most people still won't do it \ud83e\udd37\n\nDownload Seneca Chat - link in bio",
      "video_file": "social-scheduler/videos/69-pages-read-today.mp4",
      "ig_published": false,
      "fb_published": false
    },
    {
      "index": 70,
      "metric": "Apps Blocked Today",
      "hook": "No way, there's official ranks for self-control now..",
      "caption": "No way, there's official ranks for self-control now..\n\nsend this to your impulsive friend \ud83d\udc80\n\nDownload Seneca Chat - link in bio",
      "video_file": "social-scheduler/videos/70-apps-blocked-today.mp4",
      "ig_published": false,
      "fb_published": false
    },
    {
      "index": 71,
      "metric": "Apps Blocked Today",
      "hook": "How many apps did you block today? Be honest..",
      "caption": "How many apps did you block today? Be honest..\n\nzero isn't a rank \ud83d\ude2c\n\nDownload Seneca Chat - link in bio",
      "video_file": "social-scheduler/videos/71-apps-blocked-today.mp4",
      "ig_published": false,
      "fb_published": false
    },
    {
      "index": 72,
      "metric": "Apps Blocked Today",
      "hook": "Focus rankings just dropped..",
      "caption": "Focus rankings just dropped..\n\nand most of you have zero apps blocked \ud83d\udc80\n\nDownload Seneca Chat - link in bio",
      "video_file": "social-scheduler/videos/72-apps-blocked-today.mp4",
      "ig_published": false,
      "fb_published": false
    },
    {
      "index": 73,
      "metric": "Apps Blocked Today",
      "hook": "Blocking all your apps takes real discipline..",
      "caption": "Blocking all your apps takes real discipline..\n\nonly Iridescent players go that hard \ud83d\udd12\n\nDownload Seneca Chat - link in bio",
      "video_file": "social-scheduler/videos/73-apps-blocked-today.mp4",
      "ig_published": false,
      "fb_published": false
    },
    {
      "index": 74,
      "metric": "Apps Blocked Today",
      "hook": "Your app blocker count says everything about you..",
      "caption": "Your app blocker count says everything about you..\n\nwhere do you rank? \ud83d\udcf5\n\nDownload Seneca Chat - link in bio",
      "video_file": "social-scheduler/videos/74-apps-blocked-today.mp4",
      "ig_published": false,
      "fb_published": false
    },
    {
      "index": 75,
      "metric": "Apps Blocked Today",
      "hook": "Tag someone who can't put their phone down..",
      "caption": "Tag someone who can't put their phone down..\n\nthey need to see this \ud83d\udcf1\n\nDownload Seneca Chat - link in bio",
      "video_file": "social-scheduler/videos/75-apps-blocked-today.mp4",
      "ig_published": false,
      "fb_published": false
    },
    {
      "index": 76,
      "metric": "Apps Blocked Today",
      "hook": "POV: you blocked every app and actually got things done..",
      "caption": "POV: you blocked every app and actually got things done..\n\nIridescent energy \u26a1\n\nDownload Seneca Chat - link in bio",
      "video_file": "social-scheduler/videos/76-apps-blocked-today.mp4",
      "ig_published": false,
      "fb_published": false
    },
    {
      "index": 77,
      "metric": "Apps Blocked Today",
      "hook": "The secret to focus isn't willpower, it's blocking apps..",
      "caption": "The secret to focus isn't willpower, it's blocking apps..\n\nhow many do you block? \ud83c\udfaf\n\nDownload Seneca Chat - link in bio",
      "video_file": "social-scheduler/videos/77-apps-blocked-today.mp4",
      "ig_published": false,
      "fb_published": false
    },
    {
      "index": 78,
      "metric": "Apps Blocked Today",
      "hook": "Imagine actually locking yourself out of distractions..",
      "caption": "Imagine actually locking yourself out of distractions..\n\nthat's what Champions do \ud83c\udfc6\n\nDownload Seneca Chat - link in bio",
      "video_file": "social-scheduler/videos/78-apps-blocked-today.mp4",
      "ig_published": false,
      "fb_published": false
    },
    {
      "index": 79,
      "metric": "Apps Blocked Today",
      "hook": "If discipline was measured by apps blocked..",
      "caption": "If discipline was measured by apps blocked..\n\nmost people wouldn't even rank \ud83e\udd37\n\nDownload Seneca Chat - link in bio",
      "video_file": "social-scheduler/videos/79-apps-blocked-today.mp4",
      "ig_published": false,
      "fb_published": false
    },
    {
      "index": 80,
      "metric": "Quotes You Can Recite",
      "hook": "No way, there's official ranks for stoic quotes now..",
      "caption": "No way, there's official ranks for stoic quotes now..\n\nsend this to your philosophy friend \ud83d\udc80\n\nDownload Seneca Chat - link in bio",
      "video_file": "social-scheduler/videos/80-quotes-you-can-recite.mp4",
      "ig_published": false,
      "fb_published": false
    },
    {
      "index": 81,
      "metric": "Quotes You Can Recite",
      "hook": "How many quotes can you actually recite from memory?",
      "caption": "How many quotes can you actually recite from memory?\n\nscreenshots don't count \ud83d\udcf8\n\nDownload Seneca Chat - link in bio",
      "video_file": "social-scheduler/videos/81-quotes-you-can-recite.mp4",
      "ig_published": false,
      "fb_published": false
    },
    {
      "index": 82,
      "metric": "Quotes You Can Recite",
      "hook": "Stoic wisdom ranks just dropped..",
      "caption": "Stoic wisdom ranks just dropped..\n\nsaving quotes isn't the same as knowing them \ud83d\udc80\n\nDownload Seneca Chat - link in bio",
      "video_file": "social-scheduler/videos/82-quotes-you-can-recite.mp4",
      "ig_published": false,
      "fb_published": false
    },
    {
      "index": 83,
      "metric": "Quotes You Can Recite",
      "hook": "If philosophy knowledge had a tier list..",
      "caption": "If philosophy knowledge had a tier list..\n\nwhere would you rank? \ud83c\udfdb\ufe0f\n\nDownload Seneca Chat - link in bio",
      "video_file": "social-scheduler/videos/83-quotes-you-can-recite.mp4",
      "ig_published": false,
      "fb_published": false
    },
    {
      "index": 84,
      "metric": "Quotes You Can Recite",
      "hook": "People who memorize wisdom are playing life on easy mode..",
      "caption": "People who memorize wisdom are playing life on easy mode..\n\nwhat's your quote count? \ud83e\udde0\n\nDownload Seneca Chat - link in bio",
      "video_file": "social-scheduler/videos/84-quotes-you-can-recite.mp4",
      "ig_published": false,
      "fb_published": false
    },
    {
      "index": 85,
      "metric": "Quotes You Can Recite",
      "hook": "Tag someone who posts quotes but can't name the philosopher..",
      "caption": "Tag someone who posts quotes but can't name the philosopher..\n\nthey need a reality check \ud83d\ude02\n\nDownload Seneca Chat - link in bio",
      "video_file": "social-scheduler/videos/85-quotes-you-can-recite.mp4",
      "ig_published": false,
      "fb_published": false
    },
    {
      "index": 86,
      "metric": "Quotes You Can Recite",
      "hook": "POV: someone asks your favourite quote and you go blank..",
      "caption": "POV: someone asks your favourite quote and you go blank..\n\nBronze behaviour \ud83e\udd49\n\nDownload Seneca Chat - link in bio",
      "video_file": "social-scheduler/videos/86-quotes-you-can-recite.mp4",
      "ig_published": false,
      "fb_published": false
    },
    {
      "index": 87,
      "metric": "Quotes You Can Recite",
      "hook": "50 quotes memorized is Marcus Aurelius level..",
      "caption": "50 quotes memorized is Marcus Aurelius level..\n\nmost people can't even name 5 \ud83d\udc80\n\nDownload Seneca Chat - link in bio",
      "video_file": "social-scheduler/videos/87-quotes-you-can-recite.mp4",
      "ig_published": false,
      "fb_published": false
    },
    {
      "index": 88,
      "metric": "Quotes You Can Recite",
      "hook": "The wisest people carry quotes in their head, not their phone..",
      "caption": "The wisest people carry quotes in their head, not their phone..\n\nhow many do you know? \ud83d\udcdc\n\nDownload Seneca Chat - link in bio",
      "video_file": "social-scheduler/videos/88-quotes-you-can-recite.mp4",
      "ig_published": false,
      "fb_published": false
    },
    {
      "index": 89,
      "metric": "Quotes You Can Recite",
      "hook": "Knowing quotes by heart hits different in real conversations..",
      "caption": "Knowing quotes by heart hits different in real conversations..\n\nIridescent scholars understand \ud83d\udc51\n\nDownload Seneca Chat - link in bio",
      "video_file": "social-scheduler/videos/89-quotes-you-can-recite.mp4",
      "ig_published": false,
      "fb_published": false
    },
    {
      "index": 90,
      "metric": "Gratitude Entries This Week",
      "hook": "No way, there's official ranks for gratitude now..",
      "caption": "No way, there's official ranks for gratitude now..\n\nsend this to someone who never says thanks \ud83d\udc80\n\nDownload Seneca Chat - link in bio",
      "video_file": "social-scheduler/videos/90-gratitude-entries-this-week.mp4",
      "ig_published": false,
      "fb_published": false
    },
    {
      "index": 91,
      "metric": "Gratitude Entries This Week",
      "hook": "How many gratitude entries did you write this week?",
      "caption": "How many gratitude entries did you write this week?\n\nsaying 'I'm grateful' in your head doesn't count \ud83d\ude2c\n\nDownload Seneca Chat - link in bio",
      "video_file": "social-scheduler/videos/91-gratitude-entries-this-week.mp4",
      "ig_published": false,
      "fb_published": false
    },
    {
      "index": 92,
      "metric": "Gratitude Entries This Week",
      "hook": "Gratitude rankings just dropped..",
      "caption": "Gratitude rankings just dropped..\n\nand most people have zero entries \ud83d\udc80\n\nDownload Seneca Chat - link in bio",
      "video_file": "social-scheduler/videos/92-gratitude-entries-this-week.mp4",
      "ig_published": false,
      "fb_published": false
    },
    {
      "index": 93,
      "metric": "Gratitude Entries This Week",
      "hook": "The happiest people practise gratitude daily..",
      "caption": "The happiest people practise gratitude daily..\n\nwhere do you rank? \ud83d\ude4f\n\nDownload Seneca Chat - link in bio",
      "video_file": "social-scheduler/videos/93-gratitude-entries-this-week.mp4",
      "ig_published": false,
      "fb_published": false
    },
    {
      "index": 94,
      "metric": "Gratitude Entries This Week",
      "hook": "If gratitude had a scoreboard..",
      "caption": "If gratitude had a scoreboard..\n\nmost people wouldn't even show up \ud83e\udd37\n\nDownload Seneca Chat - link in bio",
      "video_file": "social-scheduler/videos/94-gratitude-entries-this-week.mp4",
      "ig_published": false,
      "fb_published": false
    },
    {
      "index": 95,
      "metric": "Gratitude Entries This Week",
      "hook": "Tag someone who complains about everything..",
      "caption": "Tag someone who complains about everything..\n\nthey need to start a gratitude practice \ud83d\ude02\n\nDownload Seneca Chat - link in bio",
      "video_file": "social-scheduler/videos/95-gratitude-entries-this-week.mp4",
      "ig_published": false,
      "fb_published": false
    },
    {
      "index": 96,
      "metric": "Gratitude Entries This Week",
      "hook": "POV: you started writing gratitude daily and life changed..",
      "caption": "POV: you started writing gratitude daily and life changed..\n\nIridescent mindset shift \u2728\n\nDownload Seneca Chat - link in bio",
      "video_file": "social-scheduler/videos/96-gratitude-entries-this-week.mp4",
      "ig_published": false,
      "fb_published": false
    },
    {
      "index": 97,
      "metric": "Gratitude Entries This Week",
      "hook": "Writing what you're grateful for takes 2 minutes..",
      "caption": "Writing what you're grateful for takes 2 minutes..\n\nand most people still won't do it \ud83e\udd26\n\nDownload Seneca Chat - link in bio",
      "video_file": "social-scheduler/videos/97-gratitude-entries-this-week.mp4",
      "ig_published": false,
      "fb_published": false
    },
    {
      "index": 98,
      "metric": "Gratitude Entries This Week",
      "hook": "Every single day is the only acceptable answer..",
      "caption": "Every single day is the only acceptable answer..\n\nIridescent or nothing \ud83d\udc51\n\nDownload Seneca Chat - link in bio",
      "video_file": "social-scheduler/videos/98-gratitude-entries-this-week.mp4",
      "ig_published": false,
      "fb_published": false
    },
    {
      "index": 99,
      "metric": "Gratitude Entries This Week",
      "hook": "Gratitude is the simplest hack for happiness..",
      "caption": "Gratitude is the simplest hack for happiness..\n\nbut most people are too lazy to write it down \ud83d\udc80\n\nDownload Seneca Chat - link in bio",
      "video_file": "social-scheduler/videos/99-gratitude-entries-this-week.mp4",
      "ig_published": false,
      "fb_published": false
    }
  ]
}